omise/__init__.py
omise/errors.py
omise/request.py
omise/version.py
omise/test/__init__.py
omise/test/helper.py
omise/test/test_account.py
omise/test/test_balance.py
omise/test/test_capability.py
omise/test/test_card.py
omise/test/test_chain.py
omise/test/test_charge.py
omise/test/test_collection.py
omise/test/test_customer.py
omise/test/test_dispute.py
omise/test/test_document.py
omise/test/test_event.py
omise/test/test_forex.py
omise/test/test_lazy_collection.py
omise/test/test_link.py
omise/test/test_occurrence.py
omise/test/test_receipt.py
omise/test/test_recipient.py
omise/test/test_refund.py
omise/test/test_request.py
omise/test/test_schedule.py
omise/test/test_search.py
omise/test/test_source.py
omise/test/test_token.py
omise/test/test_transaction.py
omise/test/test_transfer.py
omise-0.15.0.dist-info/LICENSE.txt
omise-0.15.0.dist-info/METADATA
omise-0.15.0.dist-info/WHEEL
omise-0.15.0.dist-info/top_level.txt
omise-0.15.0.dist-info/RECORD
